dirhashcalc/__init__.py
dirhashcalc/dir_hash.py
dirhashcalc-0.0.1.dev4.data/scripts/dirhashcalc
dirhashcalc-0.0.1.dev4.dist-info/LICENSE
dirhashcalc-0.0.1.dev4.dist-info/METADATA
dirhashcalc-0.0.1.dev4.dist-info/WHEEL
dirhashcalc-0.0.1.dev4.dist-info/top_level.txt
dirhashcalc-0.0.1.dev4.dist-info/RECORD
