Metadata-Version: 2.1
Name: dirhashcalc
Version: 0.0.1.dev4
Summary: Calculate directory hash
Home-page: https://github.com/parsampsh/dirhashcalc
Author: Parsa Shahmaleki
Author-email: parsampsh@gmail.com
License: UNKNOWN
Platform: UNKNOWN
Classifier: Programming Language :: Python :: 3
Classifier: Operating System :: OS Independent
Classifier: License :: OSI Approved :: MIT License
Requires-Python: >=3.6
License-File: LICENSE
